LICENSE.txt
MANIFEST.in
README.md
setup.cfg
setup.py
WordsToPdfs/WordsToPdfs.pyd
WordsToPdfs/__init__.py
WordsToPdfs.egg-info/PKG-INFO
WordsToPdfs.egg-info/SOURCES.txt
WordsToPdfs.egg-info/dependency_links.txt
WordsToPdfs.egg-info/top_level.txt
WordsToPdfs/Function/__init__.py
WordsToPdfs/Ui/WordToPdfUi.pyd
WordsToPdfs/Ui/__init__.py